README.md
setup.py
urlexpander/__init__.py
urlexpander.egg-info/PKG-INFO
urlexpander.egg-info/SOURCES.txt
urlexpander.egg-info/dependency_links.txt
urlexpander.egg-info/requires.txt
urlexpander.egg-info/top_level.txt
urlexpander/core/__init__.py
urlexpander/core/api.py
urlexpander/core/constants.py
urlexpander/core/datasets.py
urlexpander/core/html_utils.py
urlexpander/core/tweet_utils.py