Metadata-Version: 2.1
Name: urlexpander
Version: 0.0.36
Summary: urlExpander is a Python package for quickly and thoroughly expanding shortened URLs.
Home-page: https://github.com/SMAPPNYU/urlExpander
Author: leon yin
Author-email: whereisleon@gmail.com
License: MIT
Keywords: smapp social media unshorten expand link url
Platform: UNKNOWN
